README.rst
setup.cfg
setup.py
couchbase_exporter.egg-info/PKG-INFO
couchbase_exporter.egg-info/SOURCES.txt
couchbase_exporter.egg-info/dependency_links.txt
couchbase_exporter.egg-info/entry_points.txt
couchbase_exporter.egg-info/requires.txt
couchbase_exporter.egg-info/top_level.txt
prometheus_couchbase_exporter/__init__.py