Metadata-Version: 1.1
Name: couchbase-exporter
Version: 1.1.0
Summary: Couchbase query Prometheus exporter
Home-page: https://github.com/Travix-International/prometheus_couchbase_exporter
Author: Bruno Soares
Author-email: bruno.soares@jumia.com
License: MIT
Keywords: monitoring prometheus exporter
Platform: UNKNOWN
Classifier: Development Status :: 3 - Alpha
Classifier: Environment :: Web Environment
Classifier: Intended Audience :: Developers
Classifier: License :: OSI Approved :: MIT License
Classifier: Programming Language :: Python :: 2
Classifier: Programming Language :: Python :: 2.7
Classifier: Programming Language :: Python :: 3
Classifier: Programming Language :: Python :: 3.5
